{
    "configurations": [
        {
            "name": "Linux",
            "defines": [],
            "includePath": [
                "${workspaceFolder}/**",
                "/usr/include",
                "/usr/include/c++/*",
                "/usr/lib/gcc/*/include",
                "/usr/local/include"
            ],
            "compilerPath": "/usr/bin/g++",
            "cStandard": "c17",
            "cppStandard": "c++17",
            "intelliSenseMode": "linux-gcc-x64"
        }
    ],
    "version": 4
}